laser_learning_environment-2.6.1.dist-info/METADATA
laser_learning_environment-2.6.1.dist-info/WHEEL
laser_learning_environment-2.6.1.dist-info/licenses/licence
lle/__init__.py
lle/env/__init__.py
lle/env/builder.py
lle/env/env.py
lle/env/extras_generators.py
lle/env/reward_strategy.py
lle/env/utils.py
lle/exceptions.pyi
lle/lle.cpython-313t-darwin.so
lle/lle.pyi
lle/observations.py
lle/py.typed
lle/tiles.pyi
lle/types.py
laser_learning_environment-2.6.1.dist-info/RECORD
