Metadata-Version: 2.4
Name: laser-learning-environment
Version: 2.6.1
Classifier: Programming Language :: Rust
Classifier: Programming Language :: Python :: Implementation :: CPython
Classifier: Programming Language :: Python :: Implementation :: PyPy
Requires-Dist: numpy>=2.0.0
Requires-Dist: multi-agent-rlenv>=3.5.0
Requires-Dist: opencv-python>=4.0.0
Requires-Dist: orjson>=3.10.15
License-File: licence
Summary: Laser Learning Environment (LLE) for Multi-Agent Reinforcement Learning
Keywords: marl,rl,lle,laser,environment
Home-Page: https://github.com/yamoling/lle
Author-email: Yannick Molinghen <yannick.molinghen@ulb.be>
Requires-Python: >=3.10, <4
Project-URL: Source Code, https://github.com/yamoling/lle
